pulumi/__init__.py
pulumi/_types.py
pulumi/_utils.py
pulumi/_version.py
pulumi/asset.py
pulumi/config.py
pulumi/deprecated.py
pulumi/errors.py
pulumi/invoke.py
pulumi/log.py
pulumi/metadata.py
pulumi/output.py
pulumi/py.typed
pulumi/resource.py
pulumi/resource_hooks.py
pulumi/stack_reference.py
pulumi/stash.py
pulumi/type_token.py
pulumi/urn.py
pulumi/automation/__init__.py
pulumi/automation/_cmd.py
pulumi/automation/_config.py
pulumi/automation/_env.py
pulumi/automation/_local_workspace.py
pulumi/automation/_minimum_version.py
pulumi/automation/_output.py
pulumi/automation/_project_settings.py
pulumi/automation/_remote_stack.py
pulumi/automation/_remote_workspace.py
pulumi/automation/_representable.py
pulumi/automation/_server.py
pulumi/automation/_stack.py
pulumi/automation/_stack_settings.py
pulumi/automation/_tag.py
pulumi/automation/_workspace.py
pulumi/automation/errors.py
pulumi/automation/events.py
pulumi/dynamic/__init__.py
pulumi/dynamic/__main__.py
pulumi/dynamic/config.py
pulumi/dynamic/dynamic.py
pulumi/policy/__init__.py
pulumi/policy/__main__.py
pulumi/provider/__init__.py
pulumi/provider/provider.py
pulumi/provider/server.py
pulumi/provider/experimental/__init__.py
pulumi/provider/experimental/analyzer.py
pulumi/provider/experimental/component.py
pulumi/provider/experimental/host.py
pulumi/provider/experimental/property_value.py
pulumi/provider/experimental/provider.py
pulumi/provider/experimental/schema.py
pulumi/provider/experimental/server.py
pulumi/provider/experimental/util.py
pulumi/run/plugin/__main__.py
pulumi/runtime/__init__.py
pulumi/runtime/_callbacks.py
pulumi/runtime/_depends_on.py
pulumi/runtime/_grpc_settings.py
pulumi/runtime/_json.py
pulumi/runtime/_serialization.py
pulumi/runtime/config.py
pulumi/runtime/invoke.py
pulumi/runtime/known_types.py
pulumi/runtime/mocks.py
pulumi/runtime/resource.py
pulumi/runtime/resource_cycle_breaker.py
pulumi/runtime/resource_hooks.py
pulumi/runtime/rpc.py
pulumi/runtime/rpc_manager.py
pulumi-3.218.0.dist-info/METADATA
pulumi-3.218.0.dist-info/WHEEL
pulumi-3.218.0.dist-info/licenses/LICENSE
pulumi-3.218.0.dist-info/RECORD
