Metadata-Version: 2.3
Name: pulumi
Version: 3.218.0
Summary: Pulumi's Python SDK
Project-URL: Documentation, https://www.pulumi.com
Project-URL: Changelog, https://github.com/pulumi/pulumi/blob/master/CHANGELOG.md
Project-URL: GitHub, https://github.com/pulumi/pulumi
License: Apache-2.0
Classifier: Programming Language :: Python :: 3.10
Classifier: Programming Language :: Python :: 3.11
Classifier: Programming Language :: Python :: 3.12
Classifier: Programming Language :: Python :: 3.13
Classifier: Programming Language :: Python :: 3.14
Classifier: Typing :: Typed
Requires-Python: >=3.10
Requires-Dist: debugpy~=1.8.7
Requires-Dist: dill~=0.4
Requires-Dist: grpcio<2,>=1.68.1; python_version < '3.14'
Requires-Dist: grpcio<2,>=1.75.1; python_version >= '3.14'
Requires-Dist: pip<26,>=24.3.1
Requires-Dist: protobuf<6,>=3.20.3
Requires-Dist: pyyaml~=6.0
Requires-Dist: semver~=3.0
